ksrpc/__init__.py
ksrpc/_version.py
ksrpc/app.py
ksrpc/caller.py
ksrpc/client.py
ksrpc/config.py
ksrpc/run_app.py
ksrpc/run_notebook.py
ksrpc/connections/__init__.py
ksrpc/connections/http.py
ksrpc/connections/websocket.py
ksrpc/hack/WindPy.py
ksrpc/hack/__init__.py
ksrpc/hack/jqdatasdk.py
ksrpc/hack/rqdatac.py
ksrpc/hack/tushare.py
ksrpc/server/__init__.py
ksrpc/server/demo.py
ksrpc/server/test.py
ksrpc/utils/__init__.py
ksrpc/utils/async_.py
ksrpc/utils/chunks.py
ksrpc/utils/key_.py
ksrpc/utils/misc.py
ksrpc/utils/process.py
ksrpc/utils/stubs.py
ksrpc/utils/stubs_0.py
ksrpc/utils/stubs_1.py
ksrpc/utils/tqdm.py
ksrpc-0.6.12.dist-info/METADATA
ksrpc-0.6.12.dist-info/WHEEL
ksrpc-0.6.12.dist-info/licenses/LICENSE
ksrpc-0.6.12.dist-info/RECORD
