Metadata-Version: 2.4
Name: ksrpc
Version: 0.6.12
Summary: Keep Simple RPC
Author-email: wukan <wu-kan@163.com>
License: MIT License
License-File: LICENSE
Keywords: rpc
Classifier: Development Status :: 4 - Beta
Classifier: Programming Language :: Python
Requires-Python: >=3.6
Requires-Dist: aiohttp
Requires-Dist: dill>=0.3.4
Requires-Dist: loguru
Requires-Dist: nest-asyncio
Requires-Dist: pandas
Requires-Dist: psutil
Provides-Extra: stub
Requires-Dist: mypy; extra == 'stub'
